RubyZhongwenWendangRgssZhongwenWendang/README.md
RubyZhongwenWendangRgssZhongwenWendang/__init__.py
RubyZhongwenWendangRgssZhongwenWendang/__main__.py
RubyZhongwenWendangRgssZhongwenWendang/file.epub
RubyZhongwenWendangRgssZhongwenWendang/index.html
RubyZhongwenWendangRgssZhongwenWendang/css/__init__.py
RubyZhongwenWendangRgssZhongwenWendang/css/annotations.css
RubyZhongwenWendangRgssZhongwenWendang/css/main.css
RubyZhongwenWendangRgssZhongwenWendang/css/normalize.css
RubyZhongwenWendangRgssZhongwenWendang/css/popup.css
RubyZhongwenWendangRgssZhongwenWendang/font/__init__.py
RubyZhongwenWendangRgssZhongwenWendang/font/fontello.eot
RubyZhongwenWendangRgssZhongwenWendang/font/fontello.svg
RubyZhongwenWendangRgssZhongwenWendang/font/fontello.ttf
RubyZhongwenWendangRgssZhongwenWendang/font/fontello.woff
RubyZhongwenWendangRgssZhongwenWendang/img/__init__.py
RubyZhongwenWendangRgssZhongwenWendang/img/annotator-glyph-sprite.png
RubyZhongwenWendangRgssZhongwenWendang/img/annotator-icon-sprite.png
RubyZhongwenWendangRgssZhongwenWendang/img/apple-touch-icon.png
RubyZhongwenWendangRgssZhongwenWendang/img/cancelfullscreen.png
RubyZhongwenWendangRgssZhongwenWendang/img/close.png
RubyZhongwenWendangRgssZhongwenWendang/img/fullscreen.png
RubyZhongwenWendangRgssZhongwenWendang/img/loader.gif
RubyZhongwenWendangRgssZhongwenWendang/img/menu-icon.png
RubyZhongwenWendangRgssZhongwenWendang/img/save.png
RubyZhongwenWendangRgssZhongwenWendang/img/saved.png
RubyZhongwenWendangRgssZhongwenWendang/img/settings-s.png
RubyZhongwenWendangRgssZhongwenWendang/img/settings.png
RubyZhongwenWendangRgssZhongwenWendang/img/star.png
RubyZhongwenWendangRgssZhongwenWendang/js/__init__.py
RubyZhongwenWendangRgssZhongwenWendang/js/epub.js
RubyZhongwenWendangRgssZhongwenWendang/js/epub.min.js
RubyZhongwenWendangRgssZhongwenWendang/js/epub.min.map
RubyZhongwenWendangRgssZhongwenWendang/js/hooks.min.js
RubyZhongwenWendangRgssZhongwenWendang/js/hooks.min.map
ruby_zhongwen_wendang_rgss_zhongwen_wendang-2024.3.2.0.dist-info/METADATA
ruby_zhongwen_wendang_rgss_zhongwen_wendang-2024.3.2.0.dist-info/WHEEL
ruby_zhongwen_wendang_rgss_zhongwen_wendang-2024.3.2.0.dist-info/entry_points.txt
ruby_zhongwen_wendang_rgss_zhongwen_wendang-2024.3.2.0.dist-info/top_level.txt
ruby_zhongwen_wendang_rgss_zhongwen_wendang-2024.3.2.0.dist-info/RECORD
